[
  {
    "id": 1,
    "type": "single",
    "question": "What is a constraint in SQL?",
    "options": [
      "A rule applied to columns to enforce valid data",
      "A query to fetch data",
      "A type of database",
      "A command to delete rows"
    ],
    "answer": ["A rule applied to columns to enforce valid data"]
  },
  {
    "id": 2,
    "type": "single",
    "question": "What is a column constraint?",
    "options": [
      "A rule applied to a specific column",
      "A rule applied to an entire database",
      "A query condition",
      "A type of join"
    ],
    "answer": ["A rule applied to a specific column"]
  },
  {
    "id": 3,
    "type": "single",
    "question": "What is a PRIMARY KEY constraint?",
    "options": [
      "A column that uniquely identifies each row",
      "A column that allows duplicates",
      "A column used only for sorting",
      "A column used for grouping"
    ],
    "answer": ["A column that uniquely identifies each row"]
  },
  {
    "id": 4,
    "type": "single",
    "question": "Can a PRIMARY KEY accept NULL values?",
    "options": ["No", "Yes", "Sometimes", "Only once"],
    "answer": ["No"]
  },
  {
    "id": 5,
    "type": "single",
    "question": "Can a PRIMARY KEY have duplicate values?",
    "options": ["No", "Yes", "Only two duplicates", "Only if indexed"],
    "answer": ["No"]
  },
  {
    "id": 6,
    "type": "single",
    "question": "What is a composite key?",
    "options": [
      "A primary key made of multiple columns",
      "A single unique column",
      "A foreign key",
      "A temporary key"
    ],
    "answer": ["A primary key made of multiple columns"]
  },
  {
    "id": 7,
    "type": "single",
    "question": "What is UNIQUE constraint?",
    "options": [
      "Ensures all values in a column are unique",
      "Deletes duplicate rows",
      "Sorts data",
      "Groups data"
    ],
    "answer": ["Ensures all values in a column are unique"]
  },
  {
    "id": 8,
    "type": "single",
    "question": "Can UNIQUE constraint allow NULL values?",
    "options": ["Yes", "No", "Only once", "Only twice"],
    "answer": ["Yes"]
  },
  {
    "id": 9,
    "type": "single",
    "question": "What is NOT NULL constraint?",
    "options": [
      "Ensures column cannot have NULL values",
      "Allows only numbers",
      "Deletes rows",
      "Creates tables"
    ],
    "answer": ["Ensures column cannot have NULL values"]
  },
  {
    "id": 10,
    "type": "single",
    "question": "What is CHECK constraint?",
    "options": [
      "Validates data based on a condition",
      "Deletes invalid rows",
      "Creates indexes",
      "Sorts data"
    ],
    "answer": ["Validates data based on a condition"]
  },
  {
    "id": 11,
    "type": "single",
    "question": "What is a FOREIGN KEY?",
    "options": [
      "A column that links to another table",
      "A unique identifier",
      "A sorting column",
      "A default value"
    ],
    "answer": ["A column that links to another table"]
  },
  {
    "id": 12,
    "type": "single",
    "question": "What is IF EXISTS used for?",
    "options": [
      "To avoid errors when dropping objects",
      "To insert data",
      "To sort data",
      "To filter rows"
    ],
    "answer": ["To avoid errors when dropping objects"]
  },
  {
    "id": 13,
    "type": "single",
    "question": "What happens when dropping a table with foreign key dependency?",
    "options": [
      "It may fail unless dependencies are removed",
      "It always succeeds",
      "It deletes only rows",
      "It renames table"
    ],
    "answer": ["It may fail unless dependencies are removed"]
  },
  {
    "id": 14,
    "type": "single",
    "question": "What happens when deleting a parent record with foreign key?",
    "options": [
      "It may fail or cascade based on constraint",
      "It always deletes child rows",
      "It renames rows",
      "It updates values"
    ],
    "answer": ["It may fail or cascade based on constraint"]
  },
  {
    "id": 15,
    "type": "single",
    "question": "What is ON DELETE CASCADE?",
    "options": [
      "Automatically deletes child rows",
      "Prevents deletion",
      "Renames rows",
      "Sorts data"
    ],
    "answer": ["Automatically deletes child rows"]
  },
  {
    "id": 16,
    "type": "single",
    "question": "What is DEFAULT constraint?",
    "options": [
      "Assigns default value if none provided",
      "Deletes rows",
      "Creates table",
      "Sorts data"
    ],
    "answer": ["Assigns default value if none provided"]
  },
  {
    "id": 17,
    "type": "single",
    "question": "What is soft delete?",
    "options": [
      "Marking records as deleted instead of removing them",
      "Deleting records permanently",
      "Renaming records",
      "Sorting records"
    ],
    "answer": ["Marking records as deleted instead of removing them"]
  },
  {
    "id": 18,
    "type": "sql",
    "question": "Show all user IDs from the users table.\n\nSELECT id FROM users;",
    "schema_sql": "CREATE TABLE users (id INTEGER PRIMARY KEY, name TEXT);",
    "seed_data": [
      {
        "table": "users",
        "rows": [
          {
            "id": 1,
            "name": "Alice"
          },
          {
            "id": 2,
            "name": "Bob"
          }
        ]
      }
    ],
    "expected_columns": ["id"],
    "expected_rows": [[1], [2]]
  },
  {
    "id": 19,
    "type": "sql",
    "question": "Show the composite key columns from the orders table.\n\nSELECT order_id, user_id FROM orders;",
    "schema_sql": "CREATE TABLE orders (order_id INTEGER, user_id INTEGER, amount REAL, PRIMARY KEY (order_id, user_id));",
    "seed_data": [
      {
        "table": "orders",
        "rows": [
          {
            "order_id": 101,
            "user_id": 1,
            "amount": 250.0
          },
          {
            "order_id": 102,
            "user_id": 2,
            "amount": 300.0
          }
        ]
      }
    ],
    "expected_columns": ["order_id", "user_id"],
    "expected_rows": [
      [101, 1],
      [102, 2]
    ]
  },
  {
    "id": 20,
    "type": "sql",
    "question": "Show all unique email values from the users table.\n\nSELECT DISTINCT email FROM users;",
    "schema_sql": "CREATE TABLE users (id INTEGER PRIMARY KEY, email TEXT UNIQUE);",
    "seed_data": [
      {
        "table": "users",
        "rows": [
          {
            "id": 1,
            "email": "alice@example.com"
          },
          {
            "id": 2,
            "email": "bob@example.com"
          },
          {
            "id": 3,
            "email": "carol@example.com"
          }
        ]
      }
    ],
    "expected_columns": ["email"],
    "expected_rows": [
      ["alice@example.com"],
      ["bob@example.com"],
      ["carol@example.com"]
    ]
  },
  {
    "id": 21,
    "type": "sql",
    "question": "Show the names of all employees.\n\nSELECT name FROM employees;",
    "schema_sql": "CREATE TABLE employees (id INTEGER PRIMARY KEY, name TEXT NOT NULL, department TEXT);",
    "seed_data": [
      {
        "table": "employees",
        "rows": [
          {
            "id": 1,
            "name": "John",
            "department": "HR"
          },
          {
            "id": 2,
            "name": "Priya",
            "department": "IT"
          }
        ]
      }
    ],
    "expected_columns": ["name"],
    "expected_rows": [["John"], ["Priya"]]
  },
  {
    "id": 22,
    "type": "sql",
    "question": "Show product names and prices where the price is greater than 0.\n\nSELECT name, price FROM products WHERE price > 0;",
    "schema_sql": "CREATE TABLE products (id INTEGER PRIMARY KEY, name TEXT, price REAL CHECK(price > 0));",
    "seed_data": [
      {
        "table": "products",
        "rows": [
          {
            "id": 1,
            "name": "Keyboard",
            "price": 49.99
          },
          {
            "id": 2,
            "name": "Mouse",
            "price": 19.99
          }
        ]
      }
    ],
    "expected_columns": ["name", "price"],
    "expected_rows": [
      ["Keyboard", 49.99],
      ["Mouse", 19.99]
    ]
  },
  {
    "id": 23,
    "type": "sql",
    "question": "Show each order ID with the matching user ID.\n\nSELECT id, user_id FROM orders;",
    "schema_sql": "CREATE TABLE users (id INTEGER PRIMARY KEY, name TEXT); CREATE TABLE orders (id INTEGER PRIMARY KEY, user_id INTEGER, FOREIGN KEY(user_id) REFERENCES users(id));",
    "seed_data": [
      {
        "table": "users",
        "rows": [
          {
            "id": 1,
            "name": "Alice"
          },
          {
            "id": 2,
            "name": "Bob"
          }
        ]
      },
      {
        "table": "orders",
        "rows": [
          {
            "id": 201,
            "user_id": 1
          },
          {
            "id": 202,
            "user_id": 2
          }
        ]
      }
    ],
    "expected_columns": ["id", "user_id"],
    "expected_rows": [
      [201, 1],
      [202, 2]
    ]
  },
  {
    "id": 24,
    "type": "sql",
    "question": "Return a message only if the users table exists.\n\nSELECT 'users table exists' AS message FROM users LIMIT 1;",
    "schema_sql": "CREATE TABLE users (id INTEGER PRIMARY KEY, name TEXT);",
    "seed_data": [
      {
        "table": "users",
        "rows": [
          {
            "id": 1,
            "name": "Alice"
          }
        ]
      }
    ],
    "expected_columns": ["message"],
    "expected_rows": [["users table exists"]]
  },
  {
    "id": 25,
    "type": "sql",
    "question": "Show the user record where id = 1.\n\nSELECT id, name FROM users WHERE id = 1;",
    "schema_sql": "CREATE TABLE users (id INTEGER PRIMARY KEY, name TEXT);",
    "seed_data": [
      {
        "table": "users",
        "rows": [
          {
            "id": 1,
            "name": "Alice"
          },
          {
            "id": 2,
            "name": "Bob"
          }
        ]
      }
    ],
    "expected_columns": ["id", "name"],
    "expected_rows": [[1, "Alice"]]
  },
  {
    "id": 27,
    "type": "sql",
    "question": "Show all records from the drivers table.\n\nSELECT id, name FROM drivers;",
    "schema_sql": "CREATE TABLE drivers (id INTEGER PRIMARY KEY, name TEXT);",
    "seed_data": [
      {
        "table": "drivers",
        "rows": [
          {
            "id": 1,
            "name": "Kumar"
          },
          {
            "id": 2,
            "name": "Sara"
          }
        ]
      }
    ],
    "expected_columns": ["id", "name"],
    "expected_rows": [
      [1, "Kumar"],
      [2, "Sara"]
    ]
  },
  {
    "id": 28,
    "type": "sql",
    "question": "Show all rides with their driver_id values.\n\nSELECT id, driver_id FROM rides;",
    "schema_sql": "CREATE TABLE drivers (id INTEGER PRIMARY KEY, name TEXT); CREATE TABLE rides (id INTEGER PRIMARY KEY, driver_id INTEGER, destination TEXT, FOREIGN KEY(driver_id) REFERENCES drivers(id));",
    "seed_data": [
      {
        "table": "drivers",
        "rows": [
          {
            "id": 1,
            "name": "Kumar"
          }
        ]
      },
      {
        "table": "rides",
        "rows": [
          {
            "id": 1001,
            "driver_id": 1,
            "destination": "Airport"
          }
        ]
      }
    ],
    "expected_columns": ["id", "driver_id"],
    "expected_rows": [[1001, 1]]
  },
  {
    "id": 31,
    "type": "sql",
    "question": "Show child rows that would be removed by ON DELETE CASCADE for parent_id = 1.\n\nSELECT id, parent_id FROM child WHERE parent_id = 1;",
    "schema_sql": "CREATE TABLE parent (id INTEGER PRIMARY KEY, name TEXT); CREATE TABLE child (id INTEGER PRIMARY KEY, parent_id INTEGER, FOREIGN KEY(parent_id) REFERENCES parent(id) ON DELETE CASCADE);",
    "seed_data": [
      {
        "table": "parent",
        "rows": [
          {
            "id": 1,
            "name": "Parent A"
          },
          {
            "id": 2,
            "name": "Parent B"
          }
        ]
      },
      {
        "table": "child",
        "rows": [
          {
            "id": 101,
            "parent_id": 1
          },
          {
            "id": 102,
            "parent_id": 1
          },
          {
            "id": 103,
            "parent_id": 2
          }
        ]
      }
    ],
    "expected_columns": ["id", "parent_id"],
    "expected_rows": [
      [101, 1],
      [102, 1]
    ]
  },
  {
    "id": 32,
    "type": "sql",
    "question": "Show each task status, using the default value already stored in the table.\n\nSELECT id, status FROM tasks;",
    "schema_sql": "CREATE TABLE tasks (id INTEGER PRIMARY KEY, title TEXT, status TEXT DEFAULT 'pending');",
    "seed_data": [
      {
        "table": "tasks",
        "rows": [
          {
            "id": 1,
            "title": "Learn SQL",
            "status": "pending"
          },
          {
            "id": 2,
            "title": "Practice queries",
            "status": "completed"
          }
        ]
      }
    ],
    "expected_columns": ["id", "status"],
    "expected_rows": [
      [1, "pending"],
      [2, "completed"]
    ]
  },
  {
    "id": 33,
    "type": "sql",
    "question": "Show records that are not soft-deleted.\n\nSELECT id, name FROM documents WHERE isDeleted = 0;",
    "schema_sql": "CREATE TABLE documents (id INTEGER PRIMARY KEY, name TEXT, isDeleted INTEGER DEFAULT 0);",
    "seed_data": [
      {
        "table": "documents",
        "rows": [
          {
            "id": 1,
            "name": "Doc A",
            "isDeleted": 0
          },
          {
            "id": 2,
            "name": "Doc B",
            "isDeleted": 1
          },
          {
            "id": 3,
            "name": "Doc C",
            "isDeleted": 0
          }
        ]
      }
    ],
    "expected_columns": ["id", "name"],
    "expected_rows": [
      [1, "Doc A"],
      [3, "Doc C"]
    ]
  },
  {
    "id": 34,
    "type": "single",
    "question": "In real world, which is best example of FOREIGN KEY?",
    "options": [
      "Orders linked to Users",
      "Sorting a list",
      "Printing a value",
      "Updating a variable"
    ],
    "answer": ["Orders linked to Users"]
  },
  {
    "id": 35,
    "type": "single",
    "question": "Which scenario best explains UNIQUE constraint?",
    "options": [
      "Email IDs in a system must be unique",
      "User names can repeat",
      "Sorting salaries",
      "Deleting rows"
    ],
    "answer": ["Email IDs in a system must be unique"]
  }
]
